setup.py
LSE/__init__.py
LSE.egg-info/PKG-INFO
LSE.egg-info/SOURCES.txt
LSE.egg-info/dependency_links.txt
LSE.egg-info/not-zip-safe
LSE.egg-info/top_level.txt