Metadata-Version: 1.0
Name: LSE
Version: 0.0.6
Summary: Let spiders easier!
Home-page: https://letspiderseasier.github.io/LSE
Author: iYgnohZ
Author-email: iygnohz@gmail.com
License: MIT
Platform: UNKNOWN
